[
  {
    "id": "3d0e25c8-35e7-4cec-9b3d-5c4e1899964e",
    "client_order_id": "WK_STK_HOOD_1767119820",
    "created_at": "2025-12-30T18:37:00.608377Z",
    "updated_at": "2025-12-30T18:37:00.794644Z",
    "submitted_at": "2025-12-30T18:37:00.61874Z",
    "filled_at": "2025-12-30T18:37:00.79241Z",
    "expired_at": null,
    "canceled_at": null,
    "failed_at": null,
    "replaced_at": null,
    "replaced_by": null,
    "replaces": null,
    "asset_id": "c6e72c57-a1a9-4e4b-a7d0-029160f8bd64",
    "symbol": "HOOD",
    "asset_class": "us_equity",
    "notional": null,
    "qty": "17",
    "filled_qty": "17",
    "filled_avg_price": "116.58",
    "order_class": "bracket",
    "order_type": "limit",
    "type": "limit",
    "side": "buy",
    "position_intent": "buy_to_open",
    "time_in_force": "day",
    "limit_price": "119.89",
    "stop_price": null,
    "status": "filled",
    "extended_hours": false,
    "legs": [
      {
        "id": "9c6b6216-6635-4525-a0c9-d5b9fedeab81",
        "client_order_id": "211e70ee-407b-42f0-adf5-67cb26f76517",
        "created_at": "2025-12-30T18:37:00.608377Z",
        "updated_at": "2025-12-30T20:50:02.788512Z",
        "submitted_at": "2025-12-30T18:37:00.812067Z",
        "filled_at": null,
        "expired_at": null,
        "canceled_at": "2025-12-30T20:50:02.785795Z",
        "failed_at": null,
        "replaced_at": null,
        "replaced_by": null,
        "replaces": null,
        "asset_id": "c6e72c57-a1a9-4e4b-a7d0-029160f8bd64",
        "symbol": "HOOD",
        "asset_class": "us_equity",
        "notional": null,
        "qty": "17",
        "filled_qty": "0",
        "filled_avg_price": null,
        "order_class": "bracket",
        "order_type": "limit",
        "type": "limit",
        "side": "sell",
        "position_intent": "sell_to_close",
        "time_in_force": "day",
        "limit_price": "202.13",
        "stop_price": null,
        "status": "canceled",
        "extended_hours": false,
        "legs": null,
        "trail_percent": null,
        "trail_price": null,
        "hwm": null,
        "subtag": null,
        "source": "access_key",
        "expires_at": "2025-12-30T21:00:00Z"
      },
      {
        "id": "26821ae9-9541-43c0-a804-aa59e06f6cda",
        "client_order_id": "3d38c4fc-6ef1-4142-abef-050fe12878a4",
        "created_at": "2025-12-30T18:37:00.608377Z",
        "updated_at": "2025-12-30T20:50:01.783037Z",
        "submitted_at": "2025-12-30T18:37:00.608377Z",
        "filled_at": null,
        "expired_at": null,
        "canceled_at": "2025-12-30T20:50:01.783037Z",
        "failed_at": null,
        "replaced_at": null,
        "replaced_by": null,
        "replaces": null,
        "asset_id": "c6e72c57-a1a9-4e4b-a7d0-029160f8bd64",
        "symbol": "HOOD",
        "asset_class": "us_equity",
        "notional": null,
        "qty": "17",
        "filled_qty": "0",
        "filled_avg_price": null,
        "order_class": "bracket",
        "order_type": "stop",
        "type": "stop",
        "side": "sell",
        "position_intent": "sell_to_close",
        "time_in_force": "day",
        "limit_price": null,
        "stop_price": "82.42",
        "status": "canceled",
        "extended_hours": false,
        "legs": null,
        "trail_percent": null,
        "trail_price": null,
        "hwm": null,
        "subtag": null,
        "source": "access_key",
        "expires_at": "2025-12-30T21:00:00Z"
      }
    ],
    "trail_percent": null,
    "trail_price": null,
    "hwm": null,
    "subtag": null,
    "source": "access_key",
    "expires_at": "2025-12-30T21:00:00Z"
  },
  {
    "id": "6ae1e07d-186f-479a-8360-e56080ab7bce",
    "client_order_id": "15M_OPT_C260109C00117000_1767107846",
    "created_at": "2025-12-30T15:17:27.674476Z",
    "updated_at": "2025-12-30T15:21:38.037996Z",
    "submitted_at": "2025-12-30T15:17:27.694607Z",
    "filled_at": "2025-12-30T15:21:38.034758Z",
    "expired_at": null,
    "canceled_at": null,
    "failed_at": null,
    "replaced_at": null,
    "replaced_by": null,
    "replaces": null,
    "asset_id": "",
    "symbol": "",
    "asset_class": "",
    "notional": null,
    "qty": "1",
    "filled_qty": "1",
    "filled_avg_price": "0.58",
    "order_class": "mleg",
    "order_type": "",
    "type": "limit",
    "side": "",
    "time_in_force": "day",
    "limit_price": "0.58",
    "stop_price": null,
    "status": "filled",
    "extended_hours": false,
    "legs": [
      {
        "id": "04f89b19-21c8-4810-9e53-b242ae2bd31e",
        "client_order_id": "03d40bed-4b55-4d70-8f18-1da295a87704",
        "created_at": "2025-12-30T15:17:27.674476Z",
        "updated_at": "2025-12-30T15:21:38.036884Z",
        "submitted_at": "2025-12-30T15:17:27.693085Z",
        "filled_at": "2025-12-30T15:21:38.034751Z",
        "expired_at": null,
        "canceled_at": null,
        "failed_at": null,
        "replaced_at": null,
        "replaced_by": null,
        "replaces": null,
        "asset_id": "e3a723f4-9f99-48f5-b5e2-5ae7726b34ba",
        "symbol": "C260109C00117000",
        "asset_class": "us_option",
        "notional": null,
        "qty": "1",
        "filled_qty": "1",
        "filled_avg_price": "1.87",
        "order_class": "mleg",
        "order_type": "limit",
        "type": "limit",
        "side": "buy",
        "position_intent": "buy_to_open",
        "time_in_force": "day",
        "limit_price": null,
        "stop_price": null,
        "status": "filled",
        "extended_hours": false,
        "legs": null,
        "trail_percent": null,
        "trail_price": null,
        "hwm": null,
        "subtag": null,
        "source": "access_key",
        "expires_at": "2025-12-30T21:00:00Z",
        "ratio_qty": "1"
      },
      {
        "id": "75e4294b-f614-4b7f-a858-05b0b8297480",
        "client_order_id": "5c918f83-5b64-475f-8315-4e48458f2263",
        "created_at": "2025-12-30T15:17:27.674476Z",
        "updated_at": "2025-12-30T15:21:38.037949Z",
        "submitted_at": "2025-12-30T15:17:27.694607Z",
        "filled_at": "2025-12-30T15:21:38.034758Z",
        "expired_at": null,
        "canceled_at": null,
        "failed_at": null,
        "replaced_at": null,
        "replaced_by": null,
        "replaces": null,
        "asset_id": "7eb40520-178a-4feb-a3c8-d8a2b62cde2b",
        "symbol": "C260109C00118000",
        "asset_class": "us_option",
        "notional": null,
        "qty": "1",
        "filled_qty": "1",
        "filled_avg_price": "1.29",
        "order_class": "mleg",
        "order_type": "limit",
        "type": "limit",
        "side": "sell",
        "position_intent": "sell_to_open",
        "time_in_force": "day",
        "limit_price": null,
        "stop_price": null,
        "status": "filled",
        "extended_hours": false,
        "legs": null,
        "trail_percent": null,
        "trail_price": null,
        "hwm": null,
        "subtag": null,
        "source": "access_key",
        "expires_at": "2025-12-30T21:00:00Z",
        "ratio_qty": "1"
      }
    ],
    "trail_percent": null,
    "trail_price": null,
    "hwm": null,
    "subtag": null,
    "source": "access_key",
    "expires_at": "2025-12-30T21:00:00Z"
  },
  {
    "id": "27f695c7-18cc-4941-a6cc-8cd45d3da54b",
    "client_order_id": "15M_STK_C_1767107713",
    "created_at": "2025-12-30T15:15:14.385483Z",
    "updated_at": "2025-12-30T15:15:16.112385Z",
    "submitted_at": "2025-12-30T15:15:14.401083Z",
    "filled_at": "2025-12-30T15:15:16.110293Z",
    "expired_at": null,
    "canceled_at": null,
    "failed_at": null,
    "replaced_at": null,
    "replaced_by": null,
    "replaces": null,
    "asset_id": "36c8d04d-be51-476c-9382-0b6ea3bf1a26",
    "symbol": "C",
    "asset_class": "us_equity",
    "notional": null,
    "qty": "17",
    "filled_qty": "17",
    "filled_avg_price": "116.91",
    "order_class": "bracket",
    "order_type": "limit",
    "type": "limit",
    "side": "buy",
    "position_intent": "buy_to_open",
    "time_in_force": "day",
    "limit_price": "118.07",
    "stop_price": null,
    "status": "filled",
    "extended_hours": false,
    "legs": [
      {
        "id": "73f8867a-778b-4555-afde-2e1790ebab56",
        "client_order_id": "8c2f64a2-4a15-44e9-b09d-80cf3688e3dd",
        "created_at": "2025-12-30T15:15:14.385483Z",
        "updated_at": "2025-12-30T20:50:02.7827Z",
        "submitted_at": "2025-12-30T15:15:16.117732Z",
        "filled_at": null,
        "expired_at": null,
        "canceled_at": "2025-12-30T20:50:02.777411Z",
        "failed_at": null,
        "replaced_at": null,
        "replaced_by": null,
        "replaces": null,
        "asset_id": "36c8d04d-be51-476c-9382-0b6ea3bf1a26",
        "symbol": "C",
        "asset_class": "us_equity",
        "notional": null,
        "qty": "17",
        "filled_qty": "0",
        "filled_avg_price": null,
        "order_class": "bracket",
        "order_type": "limit",
        "type": "limit",
        "side": "sell",
        "position_intent": "sell_to_close",
        "time_in_force": "day",
        "limit_price": "118.08",
        "stop_price": null,
        "status": "canceled",
        "extended_hours": false,
        "legs": null,
        "trail_percent": null,
        "trail_price": null,
        "hwm": null,
        "subtag": null,
        "source": "access_key",
        "expires_at": "2025-12-30T21:00:00Z"
      },
      {
        "id": "1af65577-ff22-4989-8f72-04c45c662e91",
        "client_order_id": "eb04eb89-2812-44ec-a49b-2aeb6e9f3556",
        "created_at": "2025-12-30T15:15:14.385483Z",
        "updated_at": "2025-12-30T20:50:01.782976Z",
        "submitted_at": "2025-12-30T15:15:14.385483Z",
        "filled_at": null,
        "expired_at": null,
        "canceled_at": "2025-12-30T20:50:01.782976Z",
        "failed_at": null,
        "replaced_at": null,
        "replaced_by": null,
        "replaces": null,
        "asset_id": "36c8d04d-be51-476c-9382-0b6ea3bf1a26",
        "symbol": "C",
        "asset_class": "us_equity",
        "notional": null,
        "qty": "17",
        "filled_qty": "0",
        "filled_avg_price": null,
        "order_class": "bracket",
        "order_type": "stop",
        "type": "stop",
        "side": "sell",
        "position_intent": "sell_to_close",
        "time_in_force": "day",
        "limit_price": null,
        "stop_price": "116.34",
        "status": "canceled",
        "extended_hours": false,
        "legs": null,
        "trail_percent": null,
        "trail_price": null,
        "hwm": null,
        "subtag": null,
        "source": "access_key",
        "expires_at": "2025-12-30T21:00:00Z"
      }
    ],
    "trail_percent": null,
    "trail_price": null,
    "hwm": null,
    "subtag": null,
    "source": "access_key",
    "expires_at": "2025-12-30T21:00:00Z"
  },
  {
    "id": "a83fdf71-fc77-4a80-9fdb-e5d0633115d9",
    "client_order_id": "WK_STK_HOOD_1767106201",
    "created_at": "2025-12-30T14:50:01.307558Z",
    "updated_at": "2025-12-30T14:50:01.938467Z",
    "submitted_at": "2025-12-30T14:50:01.320041Z",
    "filled_at": "2025-12-30T14:50:01.936602Z",
    "expired_at": null,
    "canceled_at": null,
    "failed_at": null,
    "replaced_at": null,
    "replaced_by": null,
    "replaces": null,
    "asset_id": "c6e72c57-a1a9-4e4b-a7d0-029160f8bd64",
    "symbol": "HOOD",
    "asset_class": "us_equity",
    "notional": null,
    "qty": "17",
    "filled_qty": "17",
    "filled_avg_price": "117.35",
    "order_class": "bracket",
    "order_type": "limit",
    "type": "limit",
    "side": "buy",
    "position_intent": "buy_to_open",
    "time_in_force": "day",
    "limit_price": "118.53",
    "stop_price": null,
    "status": "filled",
    "extended_hours": false,
    "legs": [
      {
        "id": "24417791-32fc-4362-93bf-ca98352cc84b",
        "client_order_id": "bea18ac8-be7f-4db0-80a6-2ca2bffe7a8c",
        "created_at": "2025-12-30T14:50:01.307558Z",
        "updated_at": "2025-12-30T20:50:02.775241Z",
        "submitted_at": "2025-12-30T14:50:01.956988Z",
        "filled_at": null,
        "expired_at": null,
        "canceled_at": "2025-12-30T20:50:02.77272Z",
        "failed_at": null,
        "replaced_at": null,
        "replaced_by": null,
        "replaces": null,
        "asset_id": "c6e72c57-a1a9-4e4b-a7d0-029160f8bd64",
        "symbol": "HOOD",
        "asset_class": "us_equity",
        "notional": null,
        "qty": "17",
        "filled_qty": "0",
        "filled_avg_price": null,
        "order_class": "bracket",
        "order_type": "limit",
        "type": "limit",
        "side": "sell",
        "position_intent": "sell_to_close",
        "time_in_force": "day",
        "limit_price": "202.72",
        "stop_price": null,
        "status": "canceled",
        "extended_hours": false,
        "legs": null,
        "trail_percent": null,
        "trail_price": null,
        "hwm": null,
        "subtag": null,
        "source": "access_key",
        "expires_at": "2025-12-30T21:00:00Z"
      },
      {
        "id": "7edba0da-9750-4603-b8ce-a7fa393904d0",
        "client_order_id": "205d5f63-99f6-497f-97df-8403f13cbe63",
        "created_at": "2025-12-30T14:50:01.307558Z",
        "updated_at": "2025-12-30T20:50:01.782902Z",
        "submitted_at": "2025-12-30T14:50:01.307558Z",
        "filled_at": null,
        "expired_at": null,
        "canceled_at": "2025-12-30T20:50:01.782901Z",
        "failed_at": null,
        "replaced_at": null,
        "replaced_by": null,
        "replaces": null,
        "asset_id": "c6e72c57-a1a9-4e4b-a7d0-029160f8bd64",
        "symbol": "HOOD",
        "asset_class": "us_equity",
        "notional": null,
        "qty": "17",
        "filled_qty": "0",
        "filled_avg_price": null,
        "order_class": "bracket",
        "order_type": "stop",
        "type": "stop",
        "side": "sell",
        "position_intent": "sell_to_close",
        "time_in_force": "day",
        "limit_price": null,
        "stop_price": "83.01",
        "status": "canceled",
        "extended_hours": false,
        "legs": null,
        "trail_percent": null,
        "trail_price": null,
        "hwm": null,
        "subtag": null,
        "source": "access_key",
        "expires_at": "2025-12-30T21:00:00Z"
      }
    ],
    "trail_percent": null,
    "trail_price": null,
    "hwm": null,
    "subtag": null,
    "source": "access_key",
    "expires_at": "2025-12-30T21:00:00Z"
  },
  {
    "id": "b064420b-755a-4b2f-9fe9-93a5c57bd954",
    "client_order_id": "WK_OPT_DELL260220C00125000_1767106156",
    "created_at": "2025-12-30T14:49:16.119902Z",
    "updated_at": "2025-12-30T17:38:38.317279Z",
    "submitted_at": "2025-12-30T14:49:16.124308Z",
    "filled_at": "2025-12-30T17:38:38.313414Z",
    "expired_at": null,
    "canceled_at": null,
    "failed_at": null,
    "replaced_at": null,
    "replaced_by": null,
    "replaces": null,
    "asset_id": "e6e5e50f-23d7-47bf-b046-a6aebbe7f7cb",
    "symbol": "DELL260220C00125000",
    "asset_class": "us_option",
    "notional": null,
    "qty": "1",
    "filled_qty": "1",
    "filled_avg_price": "9.55",
    "order_class": "simple",
    "order_type": "limit",
    "type": "limit",
    "side": "buy",
    "position_intent": "buy_to_open",
    "time_in_force": "day",
    "limit_price": "9.55",
    "stop_price": null,
    "status": "filled",
    "extended_hours": false,
    "legs": null,
    "trail_percent": null,
    "trail_price": null,
    "hwm": null,
    "subtag": null,
    "source": "access_key",
    "expires_at": "2025-12-30T21:00:00Z"
  },
  {
    "id": "413bf37f-3c11-4c2b-a4f5-9e800dacfd59",
    "client_order_id": "WK_OPT_DKNG260220C00032500_1767106154",
    "created_at": "2025-12-30T14:49:14.848867Z",
    "updated_at": "2025-12-30T14:49:14.88227Z",
    "submitted_at": "2025-12-30T14:49:14.853736Z",
    "filled_at": "2025-12-30T14:49:14.880368Z",
    "expired_at": null,
    "canceled_at": null,
    "failed_at": null,
    "replaced_at": null,
    "replaced_by": null,
    "replaces": null,
    "asset_id": "19d6ba83-f585-4e53-aea9-a8e88d2387cc",
    "symbol": "DKNG260220C00032500",
    "asset_class": "us_option",
    "notional": null,
    "qty": "1",
    "filled_qty": "1",
    "filled_avg_price": "4.25",
    "order_class": "simple",
    "order_type": "limit",
    "type": "limit",
    "side": "buy",
    "position_intent": "buy_to_open",
    "time_in_force": "day",
    "limit_price": "4.27",
    "stop_price": null,
    "status": "filled",
    "extended_hours": false,
    "legs": null,
    "trail_percent": null,
    "trail_price": null,
    "hwm": null,
    "subtag": null,
    "source": "access_key",
    "expires_at": "2025-12-30T21:00:00Z"
  },
  {
    "id": "a3c785fc-cefb-4b3a-aec1-d52de96e71d0",
    "client_order_id": "WK_OPT_SMCI260220C00029000_1767106149",
    "created_at": "2025-12-30T14:49:09.419527Z",
    "updated_at": "2025-12-30T15:21:21.179597Z",
    "submitted_at": "2025-12-30T14:49:09.4244Z",
    "filled_at": "2025-12-30T15:21:21.177757Z",
    "expired_at": null,
    "canceled_at": null,
    "failed_at": null,
    "replaced_at": null,
    "replaced_by": null,
    "replaces": null,
    "asset_id": "cbc5af8c-f245-45ac-8543-f115a03a2e40",
    "symbol": "SMCI260220C00029000",
    "asset_class": "us_option",
    "notional": null,
    "qty": "1",
    "filled_qty": "1",
    "filled_avg_price": "3.8",
    "order_class": "simple",
    "order_type": "limit",
    "type": "limit",
    "side": "buy",
    "position_intent": "buy_to_open",
    "time_in_force": "day",
    "limit_price": "3.82",
    "stop_price": null,
    "status": "filled",
    "extended_hours": false,
    "legs": null,
    "trail_percent": null,
    "trail_price": null,
    "hwm": null,
    "subtag": null,
    "source": "access_key",
    "expires_at": "2025-12-30T21:00:00Z"
  },
  {
    "id": "d0802d0a-ca64-4f37-8bb3-041b57df179e",
    "client_order_id": "WK_OPT_ORCL260220C00185000_1767106143",
    "created_at": "2025-12-30T14:49:03.96054Z",
    "updated_at": "2025-12-30T20:50:01.788845Z",
    "submitted_at": "2025-12-30T14:49:03.964926Z",
    "filled_at": null,
    "expired_at": null,
    "canceled_at": "2025-12-30T20:50:01.787052Z",
    "failed_at": null,
    "replaced_at": null,
    "replaced_by": null,
    "replaces": null,
    "asset_id": "2d4c5929-c69a-44b5-af4a-d37d57233dff",
    "symbol": "ORCL260220C00185000",
    "asset_class": "us_option",
    "notional": null,
    "qty": "1",
    "filled_qty": "0",
    "filled_avg_price": null,
    "order_class": "simple",
    "order_type": "limit",
    "type": "limit",
    "side": "buy",
    "position_intent": "buy_to_open",
    "time_in_force": "day",
    "limit_price": "19.47",
    "stop_price": null,
    "status": "canceled",
    "extended_hours": false,
    "legs": null,
    "trail_percent": null,
    "trail_price": null,
    "hwm": null,
    "subtag": null,
    "source": "access_key",
    "expires_at": "2025-12-30T21:00:00Z"
  },
  {
    "id": "15ec4bce-7eeb-4a71-be24-a3acdbc4a270",
    "client_order_id": "WK_OPT_HOOD260220C00110000_1767106138",
    "created_at": "2025-12-30T14:48:58.349626Z",
    "updated_at": "2025-12-30T14:55:41.318996Z",
    "submitted_at": "2025-12-30T14:48:58.35335Z",
    "filled_at": "2025-12-30T14:55:41.316687Z",
    "expired_at": null,
    "canceled_at": null,
    "failed_at": null,
    "replaced_at": null,
    "replaced_by": null,
    "replaces": null,
    "asset_id": "4493f910-8419-41e7-b9b4-738587f5c705",
    "symbol": "HOOD260220C00110000",
    "asset_class": "us_option",
    "notional": null,
    "qty": "1",
    "filled_qty": "1",
    "filled_avg_price": "14.7",
    "order_class": "simple",
    "order_type": "limit",
    "type": "limit",
    "side": "buy",
    "position_intent": "buy_to_open",
    "time_in_force": "day",
    "limit_price": "14.71",
    "stop_price": null,
    "status": "filled",
    "extended_hours": false,
    "legs": null,
    "trail_percent": null,
    "trail_price": null,
    "hwm": null,
    "subtag": null,
    "source": "access_key",
    "expires_at": "2025-12-30T21:00:00Z"
  },
  {
    "id": "1cd152db-08d6-46fd-bc71-5e91082ac236",
    "client_order_id": "902c035f-7638-4bcd-9adb-0883ba6f7e6a",
    "created_at": "2025-12-30T14:45:10.685702Z",
    "updated_at": "2025-12-30T14:45:10.741799Z",
    "submitted_at": "2025-12-30T14:45:10.729275Z",
    "filled_at": "2025-12-30T14:45:10.738761Z",
    "expired_at": null,
    "canceled_at": null,
    "failed_at": null,
    "replaced_at": null,
    "replaced_by": null,
    "replaces": null,
    "asset_id": "",
    "symbol": "",
    "asset_class": "",
    "notional": null,
    "qty": "1",
    "filled_qty": "1",
    "filled_avg_price": "-0.17",
    "order_class": "mleg",
    "order_type": "",
    "type": "limit",
    "side": "",
    "time_in_force": "day",
    "limit_price": "0.13",
    "stop_price": null,
    "status": "filled",
    "extended_hours": false,
    "legs": [
      {
        "id": "2b5601c2-7ed2-4767-af47-0bda84d9a121",
        "client_order_id": "ced12603-5c82-47cb-8c24-6cad4902edeb",
        "created_at": "2025-12-30T14:45:10.685702Z",
        "updated_at": "2025-12-30T14:45:10.74058Z",
        "submitted_at": "2025-12-30T14:45:10.727848Z",
        "filled_at": "2025-12-30T14:45:10.738754Z",
        "expired_at": null,
        "canceled_at": null,
        "failed_at": null,
        "replaced_at": null,
        "replaced_by": null,
        "replaces": null,
        "asset_id": "fc67e603-75a3-4a04-98c6-ab1275a32504",
        "symbol": "PLTR260102C00190000",
        "asset_class": "us_option",
        "notional": null,
        "qty": "1",
        "filled_qty": "1",
        "filled_avg_price": "0.32",
        "order_class": "mleg",
        "order_type": "limit",
        "type": "limit",
        "side": "sell",
        "position_intent": "sell_to_close",
        "time_in_force": "day",
        "limit_price": null,
        "stop_price": null,
        "status": "filled",
        "extended_hours": false,
        "legs": null,
        "trail_percent": null,
        "trail_price": null,
        "hwm": null,
        "subtag": null,
        "source": "access_key",
        "expires_at": "2025-12-30T21:00:00Z",
        "ratio_qty": "1"
      },
      {
        "id": "cda36cf1-aa91-452c-86ad-f3d9fa940347",
        "client_order_id": "e694ecf5-b23d-4b76-bb3d-f76c82234851",
        "created_at": "2025-12-30T14:45:10.685702Z",
        "updated_at": "2025-12-30T14:45:10.741725Z",
        "submitted_at": "2025-12-30T14:45:10.729275Z",
        "filled_at": "2025-12-30T14:45:10.738761Z",
        "expired_at": null,
        "canceled_at": null,
        "failed_at": null,
        "replaced_at": null,
        "replaced_by": null,
        "replaces": null,
        "asset_id": "5cf6347f-60ed-4675-a52a-0bd69ad171c1",
        "symbol": "PLTR260102C00192500",
        "asset_class": "us_option",
        "notional": null,
        "qty": "1",
        "filled_qty": "1",
        "filled_avg_price": "0.15",
        "order_class": "mleg",
        "order_type": "limit",
        "type": "limit",
        "side": "buy",
        "position_intent": "buy_to_close",
        "time_in_force": "day",
        "limit_price": null,
        "stop_price": null,
        "status": "filled",
        "extended_hours": false,
        "legs": null,
        "trail_percent": null,
        "trail_price": null,
        "hwm": null,
        "subtag": null,
        "source": "access_key",
        "expires_at": "2025-12-30T21:00:00Z",
        "ratio_qty": "1"
      }
    ],
    "trail_percent": null,
    "trail_price": null,
    "hwm": null,
    "subtag": null,
    "source": "access_key",
    "expires_at": "2025-12-30T21:00:00Z"
  },
  {
    "id": "4acb58ed-636d-4803-a8a8-07253fab2e37",
    "client_order_id": "bb4b63e0-e091-4e2b-8437-82a1a3af9552",
    "created_at": "2025-12-30T14:30:09.07004Z",
    "updated_at": "2025-12-30T14:30:09.132496Z",
    "submitted_at": "2025-12-30T14:30:09.089361Z",
    "filled_at": "2025-12-30T14:30:09.129029Z",
    "expired_at": null,
    "canceled_at": null,
    "failed_at": null,
    "replaced_at": null,
    "replaced_by": null,
    "replaces": null,
    "asset_id": "",
    "symbol": "",
    "asset_class": "",
    "notional": null,
    "qty": "1",
    "filled_qty": "1",
    "filled_avg_price": "1.1",
    "order_class": "mleg",
    "order_type": "",
    "type": "limit",
    "side": "",
    "time_in_force": "day",
    "limit_price": "1.14",
    "stop_price": null,
    "status": "filled",
    "extended_hours": false,
    "legs": [
      {
        "id": "1bc0e3a1-047f-43a0-9f1f-8c00d8fa4bd1",
        "client_order_id": "c900a192-12e6-4f1a-9c58-2f475b09e9bd",
        "created_at": "2025-12-30T14:30:09.07004Z",
        "updated_at": "2025-12-30T14:30:09.131172Z",
        "submitted_at": "2025-12-30T14:30:09.087122Z",
        "filled_at": "2025-12-30T14:30:09.12902Z",
        "expired_at": null,
        "canceled_at": null,
        "failed_at": null,
        "replaced_at": null,
        "replaced_by": null,
        "replaces": null,
        "asset_id": "820d625f-b08b-4543-a19a-93732aaa2ed8",
        "symbol": "RCL260102C00282500",
        "asset_class": "us_option",
        "notional": null,
        "qty": "1",
        "filled_qty": "1",
        "filled_avg_price": "2.85",
        "order_class": "mleg",
        "order_type": "limit",
        "type": "limit",
        "side": "sell",
        "position_intent": "sell_to_close",
        "time_in_force": "day",
        "limit_price": null,
        "stop_price": null,
        "status": "filled",
        "extended_hours": false,
        "legs": null,
        "trail_percent": null,
        "trail_price": null,
        "hwm": null,
        "subtag": null,
        "source": "access_key",
        "expires_at": "2025-12-30T21:00:00Z",
        "ratio_qty": "1"
      },
      {
        "id": "cfe149dc-ae2f-437e-a731-c28b429c3ad0",
        "client_order_id": "c5020955-4f3e-479d-aec3-97c92055df66",
        "created_at": "2025-12-30T14:30:09.07004Z",
        "updated_at": "2025-12-30T14:30:09.132408Z",
        "submitted_at": "2025-12-30T14:30:09.089361Z",
        "filled_at": "2025-12-30T14:30:09.129029Z",
        "expired_at": null,
        "canceled_at": null,
        "failed_at": null,
        "replaced_at": null,
        "replaced_by": null,
        "replaces": null,
        "asset_id": "ba5bef7a-e9f9-4fac-9057-d0534e7300f5",
        "symbol": "RCL260102C00285000",
        "asset_class": "us_option",
        "notional": null,
        "qty": "1",
        "filled_qty": "1",
        "filled_avg_price": "3.95",
        "order_class": "mleg",
        "order_type": "limit",
        "type": "limit",
        "side": "buy",
        "position_intent": "buy_to_close",
        "time_in_force": "day",
        "limit_price": null,
        "stop_price": null,
        "status": "filled",
        "extended_hours": false,
        "legs": null,
        "trail_percent": null,
        "trail_price": null,
        "hwm": null,
        "subtag": null,
        "source": "access_key",
        "expires_at": "2025-12-30T21:00:00Z",
        "ratio_qty": "1"
      }
    ],
    "trail_percent": null,
    "trail_price": null,
    "hwm": null,
    "subtag": null,
    "source": "access_key",
    "expires_at": "2025-12-30T21:00:00Z"
  },
  {
    "id": "95d38fd7-e1f5-485b-9184-98868c586211",
    "client_order_id": "3d2d6128-7253-4ed9-8c87-978b18dd05fb",
    "created_at": "2025-12-30T14:30:08.274751Z",
    "updated_at": "2025-12-30T14:30:13.850523Z",
    "submitted_at": "2025-12-30T14:30:08.285372Z",
    "filled_at": "2025-12-30T14:30:13.847567Z",
    "expired_at": null,
    "canceled_at": null,
    "failed_at": null,
    "replaced_at": null,
    "replaced_by": null,
    "replaces": null,
    "asset_id": "",
    "symbol": "",
    "asset_class": "",
    "notional": null,
    "qty": "1",
    "filled_qty": "1",
    "filled_avg_price": "0.27",
    "order_class": "mleg",
    "order_type": "",
    "type": "limit",
    "side": "",
    "time_in_force": "day",
    "limit_price": "0.36",
    "stop_price": null,
    "status": "filled",
    "extended_hours": false,
    "legs": [
      {
        "id": "2f03d1d9-1b29-475d-9af5-f1fe3c852695",
        "client_order_id": "a7b90af7-31e8-43bd-9db4-fa3241e65a89",
        "created_at": "2025-12-30T14:30:08.274751Z",
        "updated_at": "2025-12-30T14:30:13.849292Z",
        "submitted_at": "2025-12-30T14:30:08.282925Z",
        "filled_at": "2025-12-30T14:30:13.847562Z",
        "expired_at": null,
        "canceled_at": null,
        "failed_at": null,
        "replaced_at": null,
        "replaced_by": null,
        "replaces": null,
        "asset_id": "9c8bd69f-c23d-4e52-bb3e-19bf500a0a6d",
        "symbol": "ON260102C00054000",
        "asset_class": "us_option",
        "notional": null,
        "qty": "1",
        "filled_qty": "1",
        "filled_avg_price": "0.6",
        "order_class": "mleg",
        "order_type": "limit",
        "type": "limit",
        "side": "sell",
        "position_intent": "sell_to_close",
        "time_in_force": "day",
        "limit_price": null,
        "stop_price": null,
        "status": "filled",
        "extended_hours": false,
        "legs": null,
        "trail_percent": null,
        "trail_price": null,
        "hwm": null,
        "subtag": null,
        "source": "access_key",
        "expires_at": "2025-12-30T21:00:00Z",
        "ratio_qty": "1"
      },
      {
        "id": "497cdfbe-7cf6-4df8-a016-785a527e8fe2",
        "client_order_id": "c2b55c21-126d-4909-8512-b4e9d5b5c8b9",
        "created_at": "2025-12-30T14:30:08.274751Z",
        "updated_at": "2025-12-30T14:30:13.850482Z",
        "submitted_at": "2025-12-30T14:30:08.285372Z",
        "filled_at": "2025-12-30T14:30:13.847567Z",
        "expired_at": null,
        "canceled_at": null,
        "failed_at": null,
        "replaced_at": null,
        "replaced_by": null,
        "replaces": null,
        "asset_id": "d94df0c5-2a20-43ae-9856-be1ca7e662f2",
        "symbol": "ON260102C00055000",
        "asset_class": "us_option",
        "notional": null,
        "qty": "1",
        "filled_qty": "1",
        "filled_avg_price": "0.87",
        "order_class": "mleg",
        "order_type": "limit",
        "type": "limit",
        "side": "buy",
        "position_intent": "buy_to_close",
        "time_in_force": "day",
        "limit_price": null,
        "stop_price": null,
        "status": "filled",
        "extended_hours": false,
        "legs": null,
        "trail_percent": null,
        "trail_price": null,
        "hwm": null,
        "subtag": null,
        "source": "access_key",
        "expires_at": "2025-12-30T21:00:00Z",
        "ratio_qty": "1"
      }
    ],
    "trail_percent": null,
    "trail_price": null,
    "hwm": null,
    "subtag": null,
    "source": "access_key",
    "expires_at": "2025-12-30T21:00:00Z"
  }
]