{
  "market_condition": "RANGE",
  "overrides": {
    "position_size_multiplier": 1.0,
    "tp_r_multiple_adjustment": 0.0,
    "breakeven_trigger_r_adjustment": 0.0
  },
  "reason": "No strong condition detected. ADX=80.6, ATR ratio=1.07.",
  "diagnostics": {
    "spy_close": 680.33,
    "sma_20": 686.65,
    "adx": 80.6,
    "pdi": 549.1,
    "mdi": 66.3,
    "atr_5": 10.05,
    "atr_20": 9.43,
    "atr_ratio": 1.066,
    "reversal_count_20": 8
  },
  "updated_at": "2026-03-03T21:55:38.157642+00:00",
  "breadth": {
    "pct_above_sma100": 50.0,
    "above_count": 0,
    "total_valid": 0,
    "total_universe": 202,
    "failed_count": 202,
    "regime": "CAUTIOUS",
    "updated_at": "2026-03-03T21:55:53.382747+00:00"
  }
}