{
  "15M_OPT": {
    "peak_pnl_today": 0.0,
    "lock_floor": 0.0,
    "lock_active": false,
    "lock_triggered": false,
    "lock_triggered_at": null
  },
  "15M_STK": {
    "peak_pnl_today": 83.5,
    "lock_floor": 41.75,
    "lock_active": true,
    "lock_triggered": false,
    "lock_triggered_at": null
  },
  "SL_ETF": {
    "peak_pnl_today": 0.0,
    "lock_floor": 0.0,
    "lock_active": false,
    "lock_triggered": false,
    "lock_triggered_at": null
  },
  "WK_OPT": {
    "peak_pnl_today": 0.0,
    "lock_floor": 0.0,
    "lock_active": false,
    "lock_triggered": false,
    "lock_triggered_at": null
  },
  "WK_STK": {
    "peak_pnl_today": 8.22,
    "lock_floor": 0.0,
    "lock_active": false,
    "lock_triggered": false,
    "lock_triggered_at": null
  }
}